leaderdata/__init__.py
leaderdata/__main__.py
leaderdata/api.py
leaderdata/conf.py
leaderdata/exceptions.py
leaderdata_sdk-0.0.1.dist-info/LICENSE
leaderdata_sdk-0.0.1.dist-info/METADATA
leaderdata_sdk-0.0.1.dist-info/WHEEL
leaderdata_sdk-0.0.1.dist-info/top_level.txt
leaderdata_sdk-0.0.1.dist-info/RECORD
