Metadata-Version: 2.1
Name: leaderdata-sdk
Version: 0.0.1
Summary: LeaderData API SDK
Home-page: https://github.com/LeaderId/leaderdata-sdk
Author: shagohead
Author-email: html.ru@gmail.com
License: UNKNOWN
Platform: UNKNOWN
Classifier: Programming Language :: Python :: 3.7
Classifier: Programming Language :: Python :: 3.8
Classifier: License :: OSI Approved :: MIT License
Classifier: Operating System :: OS Independent
Requires-Python: >=3.7
Requires-Dist: httpx (<2,>=0.11.0)
